[{"_id":"6153e41189d9b9e27d9650b9","uid":"471320666075824134","img":"https://i.imgur.com/5aqzGGf.gif","orientation":"none"},{"_id":"6153e41189d9b9e27d9650ba","uid":"1019108837388734464","img":"https://i.imgur.com/kyYhhbJ.gif","orientation":"none"},{"_id":"6153e41189d9b9e27d9650bb","uid":"863666978531180544","img":"https://i.imgur.com/SpxdluT.gif","orientation":"none"},{"_id":"6153e41189d9b9e27d9650bc","uid":"471318396840050690","img":"https://i.imgur.com/qAcIULE.gif","orientation":"none"},{"_id":"6153e41189d9b9e27d9650bd","uid":"965189150041063424","img":"https://i.imgur.com/lLaf2Q8.gif","orientation":"none"},{"_id":"6153e41189d9b9e27d9650be","uid":"592544036167090185","img":"https://i.imgur.com/7r6CFGn.gif","orientation":"none"},{"_id":"6153e41189d9b9e27d9650bf","uid":"1186273523082199181","img":"https://i.imgur.com/Hoz2FAX.png","orientation":"none"},{"_id":"6153e41189d9b9e27d9650ca","uid":"320085757748314117","img":"https://i.imgur.com/IBDbDWU.gif","orientation":"none"},{"_id":"6153e41189d9b9e27d9650cb","uid":"748102276471717939","img":"https://i.imgur.com/O3VUVQ8.gif","orientation":"none"}]